hyprland/__init__.py
hyprland/binds.py
hyprland/config.py
hyprland/dispatch.py
hyprland/event.py
hyprland/info.py
hyprland/settings.py
hyprland/sockets.py
hyprland/window.py
hyprland/workspace.py
hyprland/util/scraper.py
hyprland/util/values.py
hyprland-0.2.54.dist-info/LICENCE
hyprland-0.2.54.dist-info/METADATA
hyprland-0.2.54.dist-info/WHEEL
hyprland-0.2.54.dist-info/top_level.txt
hyprland-0.2.54.dist-info/RECORD
