Metadata-Version: 2.1
Name: hyprland
Version: 0.2.54
Summary: An unofficial async python wrapper for Hyprland's IPC supposed to somewhat work like awesomewm api in lua
Author-email: flicko <flickerdroid211@gmail.com>
Project-URL: Homepage, https://github.com/hyprland-community/hyprland-py
Project-URL: Bug Tracker, https://github.com/hyprland-community/hyprland-py/issues
Classifier: Programming Language :: Python :: 3
Classifier: License :: OSI Approved :: MIT License
Classifier: Operating System :: Unix
Requires-Python: >=3.10
License-File: LICENCE
